apiverve_currencyconverter/__init__.py
apiverve_currencyconverter/apiClient.py
apiverve_currencyconverter/exceptions.py
apiverve_currencyconverter/setup.py
apiverve_currencyconverter/setup_dep.py
apiverve_currencyconverter/tests/__init__.py
apiverve_currencyconverter/tests/test_api.py
apiverve_currencyconverter-1.1.7.dist-info/LICENSE
apiverve_currencyconverter-1.1.7.dist-info/METADATA
apiverve_currencyconverter-1.1.7.dist-info/WHEEL
apiverve_currencyconverter-1.1.7.dist-info/top_level.txt
apiverve_currencyconverter-1.1.7.dist-info/RECORD
